scorecode/__init__.py
scorecode/models.py
scorecode/ossf_scorecard.py
scorecode/utils.py
scorecode/contrib/__init__.py
scorecode/contrib/django/__init__.py
scorecode/contrib/django/models.py
scorecode-0.0.4.dist-info/licenses/LICENSE
scorecode-0.0.4.dist-info/METADATA
scorecode-0.0.4.dist-info/WHEEL
scorecode-0.0.4.dist-info/top_level.txt
scorecode-0.0.4.dist-info/RECORD
